rreader_src/__init__.py
rreader_src/common.py
rreader_src/config.py
rreader_src/feeds.json
rreader_src/get_rss.py
rreader_src/run.py
rreader-1.1.2.dist-info/LICENSE
rreader-1.1.2.dist-info/METADATA
rreader-1.1.2.dist-info/WHEEL
rreader-1.1.2.dist-info/entry_points.txt
rreader-1.1.2.dist-info/top_level.txt
rreader-1.1.2.dist-info/RECORD
